definitions.vh
// definitions.vh
`ifndef DEFINITIONS_VH
`define DEFINITIONS_VH

// Opcode Definitions (4 bits)
`define OP_ADD   4'b0000
`define OP_SUB   4'b0001
`define OP_MUL   4'b0010
`define OP_CMP   4'b0011
`define OP_JMP   4'b0100
`define OP_JLT   4'b0101  // Jump if Less Than
`define OP_LDR   4'b0110
`define OP_STR   4'b0111
`define OP_HALT  4'b1111

// Data Widths
`define DATA_WIDTH 16
`define ADDR_WIDTH 16
`define REG_COUNT 16

`define NUM_THREADS 8      // Number of threads
`define THREAD_ID_WIDTH 3  // Width to represent thread IDs (log2(NUM_THREADS))

`endif

src/decoder.v
// decoder.v
`include "definitions.vh"

module decoder (
    input [`DATA_WIDTH-1:0] instruction,
    output reg [3:0] opcode,
    output reg [3:0] dest_reg,
    output reg [3:0] src_reg,
    output reg [7:0] immediate
);
    always @(*) begin
        opcode = instruction[15:12];
        dest_reg = instruction[11:8];
        src_reg = instruction[7:4];
        immediate = instruction[7:0]; // For instructions with immediate values
    end
endmodule

src/fetcher.v
// fetcher.v
`include "definitions.vh"

module fetcher (
    input [`ADDR_WIDTH-1:0] pc_in,
    output [`DATA_WIDTH-1:0] instruction,
    input [`DATA_WIDTH-1:0] instr_mem [0:15]
);
    assign instruction = instr_mem[pc_in];
endmodule

src/scheduler.v
// scheduler.v
`include "definitions.vh"

module scheduler #(
    parameter NUM_THREADS = `NUM_THREADS
)(
    input clk,
    input reset,
    input [NUM_THREADS-1:0] active_threads,
    output reg [`THREAD_ID_WIDTH-1:0] scheduled_thread
);
    integer last_thread; // Tracks the last scheduled thread
    integer i;           // Loop variable
    integer thread;      // Current thread being checked
    reg thread_found;    // Flag to indicate if a thread has been found

    always @(posedge clk or posedge reset) begin
        if (reset) begin
            last_thread <= -1;
            scheduled_thread <= 0;
        end else begin
            // Initialize the thread_found flag to 0 at the start of each cycle
            thread_found = 0;
            
            // Iterate through all threads in a round-robin fashion
            for (i = 1; i <= NUM_THREADS; i = i + 1) begin
                thread = (last_thread + i) % NUM_THREADS; // Calculate the next thread index
                
                // Check if the current thread is active and no thread has been scheduled yet
                if (active_threads[thread] && !thread_found) begin
                    scheduled_thread <= thread;    // Schedule this thread
                    last_thread <= thread;         // Update the last scheduled thread
                    thread_found = 1;              // Set the flag to indicate a thread has been found
                end
            end
        end
    end
endmodule

src/compute_core.v
// compute_core.v
`include "definitions.vh"

module compute_core (
    input clk,
    input reset,
    output reg halt
);
    // Internal registers and memories
    reg [`DATA_WIDTH-1:0] register_file [0:`NUM_THREADS-1][0:`REG_COUNT-1];
    reg [`ADDR_WIDTH-1:0] pc [0:`NUM_THREADS-1];
    reg [`NUM_THREADS-1:0] active_threads;
    reg [`DATA_WIDTH-1:0] data_mem [0:15]; // Shared data memory
    reg [`DATA_WIDTH-1:0] instr_mem [0:15]; // Shared instruction memory

    // Scheduler signals
    wire [`THREAD_ID_WIDTH-1:0] scheduled_thread;

    // Fetcher and Decoder signals
    wire [`DATA_WIDTH-1:0] instruction;
    wire [3:0] opcode;
    wire [3:0] dest_reg;
    wire [3:0] src_reg;
    wire [7:0] immediate;

    // ALU signals
    reg [`DATA_WIDTH-1:0] alu_result;
    reg cmp_flag;

    // Loop variables
    integer i;
    integer current_thread;

    // PC increment control
    reg pc_increment;

    // Temporary register for updated active_threads
    reg [`NUM_THREADS-1:0] next_active_threads;

    // Instantiate Scheduler
    scheduler #(
        .NUM_THREADS(`NUM_THREADS)
    ) scheduler_inst (
        .clk(clk),
        .reset(reset),
        .active_threads(active_threads),
        .scheduled_thread(scheduled_thread)
    );

    // Fetch instruction based on the scheduled thread's PC
    fetcher fetcher_inst (
        .pc_in(pc[scheduled_thread]),
        .instruction(instruction),
        .instr_mem(instr_mem)
    );

    // Decode the instruction
    decoder decoder_inst (
        .instruction(instruction),
        .opcode(opcode),
        .dest_reg(dest_reg),
        .src_reg(src_reg),
        .immediate(immediate)
    );

    // Initialize Instruction Memory
    initial begin
       $readmemh("instruction_memory.mem", instr_mem);
       $display("Instruction Memory Initialized:");
       for (i = 0; i < 16; i = i + 1) begin
           $display("instr_mem[%0d] = %h", i, instr_mem[i]);
       end
    end

    // Initialize Data Memory
    initial begin
       $readmemh("data_memory.mem", data_mem);
       $display("Data Memory Initialized:");
       for (i = 0; i < 16; i = i + 1) begin
           $display("data_mem[%0d] = %h", i, data_mem[i]);
       end
    end

    // Compute Core Logic
    always @(posedge clk or posedge reset) begin
        if (reset) begin
            // Initialize PCs and active threads
            for (i = 0; i < `NUM_THREADS; i = i + 1) begin
                pc[i] <= 0;
                active_threads[i] <= 1; // All threads are active initially
                // Initialize registers
                for (current_thread = 0; current_thread < `REG_COUNT; current_thread = current_thread + 1) begin
                    register_file[i][current_thread] <= 0;
                end
                // Assign thread ID to R15
                register_file[i][15] <= i;
            end
            halt <= 0;
            $display("DUT Reset at time %0t", $time);
        end else if (!halt) begin
            // Initialize next_active_threads with current active_threads
            next_active_threads = active_threads;

            current_thread = scheduled_thread;
            if (active_threads[current_thread]) begin
                pc_increment = 1; // Default to increment

                // Execution
                case (opcode)
                    `OP_ADD: begin
                        alu_result = register_file[current_thread][dest_reg] + register_file[current_thread][src_reg] + immediate;
                        register_file[current_thread][dest_reg] <= alu_result;
                    end
                    `OP_SUB: begin
                        alu_result = register_file[current_thread][dest_reg] - register_file[current_thread][src_reg] - immediate;
                        register_file[current_thread][dest_reg] <= alu_result;
                    end
                    `OP_MUL: begin
                        alu_result = register_file[current_thread][dest_reg] * register_file[current_thread][src_reg];
                        register_file[current_thread][dest_reg] <= alu_result;
                    end
                    `OP_CMP: begin
                        if (register_file[current_thread][dest_reg] < register_file[current_thread][src_reg]) begin
                            cmp_flag <= 1;
                        end else begin
                            cmp_flag <= 0;
                        end
                    end
                    `OP_JMP: begin
                        pc[current_thread] <= {8'b00000000, immediate}; // Assuming immediate is lower 8 bits
                        pc_increment <= 0;
                    end
                    `OP_JLT: begin
                        if (cmp_flag == 1) begin
                            pc[current_thread] <= {8'b00000000, immediate};
                            pc_increment <= 0;
                        end
                    end
                    `OP_LDR: begin
                        register_file[current_thread][dest_reg] <= data_mem[immediate];
                    end
                    `OP_STR: begin
                        data_mem[immediate] <= register_file[current_thread][dest_reg];
                    end
                    `OP_HALT: begin
                        next_active_threads[current_thread] = 0; // Halt the current thread
                        $display("Thread %0d executing HALT. Halting.", current_thread);
                    end
                    default: begin
                        // NOP or undefined instruction
                        $display("Thread %0d encountered undefined opcode %b. No operation performed.", current_thread, opcode);
                    end
                endcase

                // Increment PC if not updated by control instructions
                if (pc_increment) begin
                    pc[current_thread] <= pc[current_thread] + 1;
                end

                // Execution Logging
                $display("Time=%0t | Thread=%0d | PC=%0d | Instruction=%h | Opcode=%b | dest_reg=R%0d | src_reg=R%0d | immediate=%d",
                         $time, current_thread, pc[current_thread], instruction, opcode, dest_reg, src_reg, immediate);
            end

            // Update active_threads
            active_threads <= next_active_threads;

            // Check if all threads have halted
            if (next_active_threads == 0) begin
                halt <= 1;
                $display("All threads have halted at time %0t", $time);
            end
        end
    end

    // Dump waveforms for GTKWave
    initial begin
        $dumpfile("simulation.vcd");
        $dumpvars(0, compute_core); // Replace 'compute_core' with your top-level module name if different
    end

endmodule

simulation.vcd
$date
	Sat Nov 16 22:45:59 2024
$end
$version
	Icarus Verilog
$end
$timescale
	1ps
$end
$scope module compute_core $end
$var wire 1 ! clk $end
$var wire 1 " reset $end
$var wire 4 # src_reg [3:0] $end
$var wire 3 $ scheduled_thread [2:0] $end
$var wire 4 % opcode [3:0] $end
$var wire 16 & instruction [15:0] $end
$var wire 8 ' immediate [7:0] $end
$var wire 4 ( dest_reg [3:0] $end
$var reg 8 ) active_threads [7:0] $end
$var reg 16 * alu_result [15:0] $end
$var reg 1 + cmp_flag $end
$var reg 1 , halt $end
$var reg 8 - next_active_threads [7:0] $end
$var reg 1 . pc_increment $end
$var integer 32 / current_thread [31:0] $end
$var integer 32 0 i [31:0] $end
$scope module decoder_inst $end
$var wire 16 1 instruction [15:0] $end
$var reg 4 2 dest_reg [3:0] $end
$var reg 8 3 immediate [7:0] $end
$var reg 4 4 opcode [3:0] $end
$var reg 4 5 src_reg [3:0] $end
$upscope $end
$scope module fetcher_inst $end
$var wire 16 6 instruction [15:0] $end
$var wire 16 7 pc_in [15:0] $end
$upscope $end
$scope module scheduler_inst $end
$var wire 8 8 active_threads [7:0] $end
$var wire 1 ! clk $end
$var wire 1 " reset $end
$var parameter 32 9 NUM_THREADS $end
$var reg 3 : scheduled_thread [2:0] $end
$var reg 1 ; thread_found $end
$var integer 32 < i [31:0] $end
$var integer 32 = last_thread [31:0] $end
$var integer 32 > thread [31:0] $end
$upscope $end
$upscope $end
$enddefinitions $end
$comment Show the parameter values. $end
$dumpall
b1000 9
$end
#0
$dumpvars
bx >
b11111111111111111111111111111111 =
bx <
x;
b0 :
b11111111 8
b0 7
b101000000000110 6
b0 5
b101 4
b110 3
b0 2
b101000000000110 1
b1000 0
b10000 /
x.
bx -
0,
x+
bx *
b11111111 )
b0 (
b110 '
b101000000000110 &
b101 %
b0 $
b0 #
0"
1!
$end
#5000
0!
#10000
b1111 '
b1111 3
b100 %
b100 4
b100000000001111 &
b100000000001111 1
b100000000001111 6
b1 7
b0 =
1.
b0 /
b11111111 -
b111 >
b1001 <
1;
1!
#15000
0!
#20000
b110 '
b110 3
b101 %
b101 4
b1 =
b1 $
b1 :
0.
b101000000000110 &
b101000000000110 1
b101000000000110 6
b0 7
b0 >
b1001 <
1;
1!
#25000
0!
#30000
b10 =
b10 $
b10 :
1.
b1 /
b1 >
b1001 <
1;
1!
#35000
0!
#40000
b11 =
b11 $
b11 :
b101000000000110 &
b101000000000110 1
b101000000000110 6
b0 7
b10 >
b1001 <
1;
b10 /
1!
#45000
0!
#50000
b100 =
b100 $
b100 :
b11 /
b11 >
b1001 <
1;
1!
#55000
0!
#60000
b101 =
b101 $
b101 :
b101000000000110 &
b101000000000110 1
b101000000000110 6
b0 7
b100 >
b1001 <
1;
b100 /
1!
#65000
0!
#70000
b110 =
b110 $
b110 :
b101 /
b101 >
b1001 <
1;
1!
#75000
0!
#80000
b111 =
b111 $
b111 :
b101000000000110 &
b101000000000110 1
b101000000000110 6
b0 7
b110 >
b1001 <
1;
b110 /
1!
#85000
0!
#90000
b0 '
b0 3
b1001 %
b1001 4
b0 =
b1001000000000000 &
b1001000000000000 1
b1001000000000000 6
b10 7
b0 $
b0 :
b111 /
b111 >
b1001 <
1;
1!
#95000
0!
#100000
b1111 '
b1111 3
b100 %
b100 4
b1 =
b1 $
b1 :
b100000000001111 &
b100000000001111 1
b100000000001111 6
b1 7
b0 >
b1001 <
1;
b0 /
1!
#105000
0!
#110000
0.
b10 =
b10 $
b10 :
b1 /
b1 >
b1001 <
1;
1!
#115000
0!
#120000
b11 =
b11 $
b11 :
b100000000001111 &
b100000000001111 1
b100000000001111 6
b1 7
b10 >
b1001 <
1;
0.
b10 /
1!
#125000
0!
#130000
b100 =
b100 $
b100 :
0.
b11 /
b11 >
b1001 <
1;
1!
#135000
0!
#140000
b101 =
b101 $
b101 :
b100000000001111 &
b100000000001111 1
b100000000001111 6
b1 7
b100 >
b1001 <
1;
0.
b100 /
1!
#145000
0!
#150000
b110 =
b110 $
b110 :
0.
b101 /
b101 >
b1001 <
1;
1!
#155000
0!
#160000
b111 =
b111 $
b111 :
b100000000001111 &
b100000000001111 1
b100000000001111 6
b1 7
b110 >
b1001 <
1;
0.
b110 /
1!
#165000
0!
#170000
b1000 '
b1000 3
b10 (
b10 2
b1001 %
b1001 4
b0 =
b1001001000001000 &
b1001001000001000 1
b1001001000001000 6
b11 7
b0 $
b0 :
0.
b111 /
b111 >
b1001 <
1;
1!
#175000
0!
#180000
b0 '
b0 3
b0 (
b0 2
b1 =
b1 $
b1 :
b1001000000000000 &
b1001000000000000 1
b1001000000000000 6
b10 7
b0 >
b1001 <
1;
1.
b0 /
1!
#185000
0!
#190000
b10 =
b10 $
b10 :
b1 /
b1 >
b1001 <
1;
1!
#195000
0!
#200000
b11 =
b11 $
b11 :
b1001000000000000 &
b1001000000000000 1
b1001000000000000 6
b10 7
b10 >
b1001 <
1;
b10 /
1!
#205000
0!
#210000
b100 =
b100 $
b100 :
b11 /
b11 >
b1001 <
1;
1!
#215000
0!
#220000
b101 =
b101 $
b101 :
b1001000000000000 &
b1001000000000000 1
b1001000000000000 6
b10 7
b100 >
b1001 <
1;
b100 /
1!
#225000
0!
#230000
b110 =
b110 $
b110 :
b101 /
b101 >
b1001 <
1;
1!
#235000
0!
#240000
b111 =
b111 $
b111 :
b1001000000000000 &
b1001000000000000 1
b1001000000000000 6
b10 7
b110 >
b1001 <
1;
b110 /
1!
#245000
0!
#250000
b1 '
b1 3
b11 (
b11 2
b0 =
b1001001100000001 &
b1001001100000001 1
b1001001100000001 6
b100 7
b0 $
b0 :
b111 /
b111 >
b1001 <
1;
1!
#255000
0!
#260000
b1000 '
b1000 3
b10 (
b10 2
b1 =
b1 $
b1 :
b1001001000001000 &
b1001001000001000 1
b1001001000001000 6
b11 7
b0 >
b1001 <
1;
b0 /
1!
#265000
0!
#270000
b10 =
b10 $
b10 :
b1 /
b1 >
b1001 <
1;
1!
#275000
0!
#280000
b11 =
b11 $
b11 :
b1001001000001000 &
b1001001000001000 1
b1001001000001000 6
b11 7
b10 >
b1001 <
1;
b10 /
1!
#285000
0!
#290000
b100 =
b100 $
b100 :
b11 /
b11 >
b1001 <
1;
1!
#295000
0!
#300000
b101 =
b101 $
b101 :
b1001001000001000 &
b1001001000001000 1
b1001001000001000 6
b11 7
b100 >
b1001 <
1;
b100 /
1!
#305000
0!
#310000
b110 =
b110 $
b110 :
b101 /
b101 >
b1001 <
1;
1!
#315000
0!
#320000
b111 =
b111 $
b111 :
b1001001000001000 &
b1001001000001000 1
b1001001000001000 6
b11 7
b110 >
b1001 <
1;
b110 /
1!
#325000
0!
#330000
b10000 '
b10000 3
b1 #
b1 5
b0 (
b0 2
b1010 %
b1010 4
b0 =
b1010000000010000 &
b1010000000010000 1
b1010000000010000 6
b101 7
b0 $
b0 :
b111 /
b111 >
b1001 <
1;
1!
#335000
0!
#340000
b1 '
b1 3
b0 #
b0 5
b11 (
b11 2
b1001 %
b1001 4
b1 =
b1 $
b1 :
b1001001100000001 &
b1001001100000001 1
b1001001100000001 6
b100 7
b0 >
b1001 <
1;
b0 /
1!
#345000
0!
#350000
b10 =
b10 $
b10 :
b1 /
b1 >
b1001 <
1;
1!
#355000
0!
#360000
b11 =
b11 $
b11 :
b1001001100000001 &
b1001001100000001 1
b1001001100000001 6
b100 7
b10 >
b1001 <
1;
b10 /
1!
#365000
0!
#370000
b100 =
b100 $
b100 :
b11 /
b11 >
b1001 <
1;
1!
#375000
0!
#380000
b101 =
b101 $
b101 :
b1001001100000001 &
b1001001100000001 1
b1001001100000001 6
b100 7
b100 >
b1001 <
1;
b100 /
1!
#385000
0!
#390000
b110 =
b110 $
b110 :
b101 /
b101 >
b1001 <
1;
1!
#395000
0!
#400000
b111 =
b111 $
b111 :
b1001001100000001 &
b1001001100000001 1
b1001001100000001 6
b100 7
b110 >
b1001 <
1;
b110 /
1!
#405000
0!
#410000
b1000000 '
b1000000 3
b100 #
b100 5
b0 (
b0 2
b1011 %
b1011 4
b0 =
b1011000001000000 &
b1011000001000000 1
b1011000001000000 6
b110 7
b0 $
b0 :
b111 /
b111 >
b1001 <
1;
1!
#415000
0!
#420000
b10000 '
b10000 3
b1 #
b1 5
b1010 %
b1010 4
b1 =
b1 $
b1 :
b1010000000010000 &
b1010000000010000 1
b1010000000010000 6
b101 7
b0 >
b1001 <
1;
b0 /
1!
#425000
0!
#430000
b10 =
b10 $
b10 :
b1 /
b1 >
b1001 <
1;
1!
#435000
0!
#440000
b11 =
b11 $
b11 :
b1010000000010000 &
b1010000000010000 1
b1010000000010000 6
b101 7
b10 >
b1001 <
1;
b10 /
1!
#445000
0!
#450000
b100 =
b100 $
b100 :
b11 /
b11 >
b1001 <
1;
1!
#455000
0!
#460000
b101 =
b101 $
b101 :
b1010000000010000 &
b1010000000010000 1
b1010000000010000 6
b101 7
b100 >
b1001 <
1;
b100 /
1!
#465000
0!
#470000
b110 =
b110 $
b110 :
b101 /
b101 >
b1001 <
1;
1!
#475000
0!
#480000
b111 =
b111 $
b111 :
b1010000000010000 &
b1010000000010000 1
b1010000000010000 6
b101 7
b110 >
b1001 <
1;
b110 /
1!
#485000
0!
#490000
b1010000 '
b1010000 3
b101 #
b101 5
b0 =
b1010000001010000 &
b1010000001010000 1
b1010000001010000 6
b111 7
b0 $
b0 :
b111 /
b111 >
b1001 <
1;
1!
#495000
0!
#500000
b1000000 '
b1000000 3
b100 #
b100 5
b1011 %
b1011 4
b1 =
b1 $
b1 :
b1011000001000000 &
b1011000001000000 1
b1011000001000000 6
b110 7
b0 >
b1001 <
1;
b0 /
1!
#505000
0!
#510000
b10 =
b10 $
b10 :
b1 /
b1 >
b1001 <
1;
1!
#515000
0!
#520000
b11 =
b11 $
b11 :
b1011000001000000 &
b1011000001000000 1
b1011000001000000 6
b110 7
b10 >
b1001 <
1;
b10 /
1!
#525000
0!
#530000
b100 =
b100 $
b100 :
b11 /
b11 >
b1001 <
1;
1!
#535000
0!
#540000
b101 =
b101 $
b101 :
b1011000001000000 &
b1011000001000000 1
b1011000001000000 6
b110 7
b100 >
b1001 <
1;
b100 /
1!
#545000
0!
#550000
b110 =
b110 $
b110 :
b101 /
b101 >
b1001 <
1;
1!
#555000
0!
#560000
b111 =
b111 $
b111 :
b1011000001000000 &
b1011000001000000 1
b1011000001000000 6
b110 7
b110 >
b1001 <
1;
b110 /
1!
#565000
0!
#570000
b1010000 '
b1010000 3
b101 #
b101 5
b0 =
b1011000001010000 &
b1011000001010000 1
b1011000001010000 6
b1000 7
b0 $
b0 :
b111 /
b111 >
b1001 <
1;
1!
#575000
0!
#580000
b1010 %
b1010 4
b1 =
b1 $
b1 :
b1010000001010000 &
b1010000001010000 1
b1010000001010000 6
b111 7
b0 >
b1001 <
1;
b0 /
1!
#585000
0!
#590000
b10 =
b10 $
b10 :
b1 /
b1 >
b1001 <
1;
1!
#595000
0!
#600000
b11 =
b11 $
b11 :
b1010000001010000 &
b1010000001010000 1
b1010000001010000 6
b111 7
b10 >
b1001 <
1;
b10 /
1!
#605000
0!
#610000
b100 =
b100 $
b100 :
b11 /
b11 >
b1001 <
1;
1!
#615000
0!
#620000
b101 =
b101 $
b101 :
b1010000001010000 &
b1010000001010000 1
b1010000001010000 6
b111 7
b100 >
b1001 <
1;
b100 /
1!
#625000
0!
#630000
b110 =
b110 $
b110 :
b101 /
b101 >
b1001 <
1;
1!
#635000
0!
#640000
b111 =
b111 $
b111 :
b1010000001010000 &
b1010000001010000 1
b1010000001010000 6
b111 7
b110 >
b1001 <
1;
b110 /
1!
#645000
0!
#650000
b1100101 '
b1100101 3
b110 #
b110 5
b0 =
b1010000001100101 &
b1010000001100101 1
b1010000001100101 6
b1001 7
b0 $
b0 :
b111 /
b111 >
b1001 <
1;
1!
#655000
0!
#660000
b1010000 '
b1010000 3
b101 #
b101 5
b1011 %
b1011 4
b1 =
b1 $
b1 :
b1011000001010000 &
b1011000001010000 1
b1011000001010000 6
b1000 7
b0 >
b1001 <
1;
b0 /
1!
#665000
0!
#670000
b10 =
b10 $
b10 :
b1 /
b1 >
b1001 <
1;
1!
#675000
0!
#680000
b11 =
b11 $
b11 :
b1011000001010000 &
b1011000001010000 1
b1011000001010000 6
b1000 7
b10 >
b1001 <
1;
b10 /
1!
#685000
0!
#690000
b100 =
b100 $
b100 :
b11 /
b11 >
b1001 <
1;
1!
#695000
0!
#700000
b101 =
b101 $
b101 :
b1011000001010000 &
b1011000001010000 1
b1011000001010000 6
b1000 7
b100 >
b1001 <
1;
b100 /
1!
#705000
0!
#710000
b110 =
b110 $
b110 :
b101 /
b101 >
b1001 <
1;
1!
#715000
0!
#720000
b111 =
b111 $
b111 :
b1011000001010000 &
b1011000001010000 1
b1011000001010000 6
b1000 7
b110 >
b1001 <
1;
b110 /
1!
#725000
0!
#730000
b1110000 '
b1110000 3
b111 #
b111 5
b1010 %
b1010 4
b0 =
b1010000001110000 &
b1010000001110000 1
b1010000001110000 6
b1010 7
b0 $
b0 :
b111 /
b111 >
b1001 <
1;
1!
#735000
0!
#740000
b1100101 '
b1100101 3
b110 #
b110 5
b1 =
b1 $
b1 :
b1010000001100101 &
b1010000001100101 1
b1010000001100101 6
b1001 7
b0 >
b1001 <
1;
b0 /
1!
#745000
0!
#750000
b10 =
b10 $
b10 :
b1 /
b1 >
b1001 <
1;
1!
#755000
0!
#760000
b11 =
b11 $
b11 :
b1010000001100101 &
b1010000001100101 1
b1010000001100101 6
b1001 7
b10 >
b1001 <
1;
b10 /
1!
#765000
0!
#770000
b100 =
b100 $
b100 :
b11 /
b11 >
b1001 <
1;
1!
#775000
0!
#780000
b101 =
b101 $
b101 :
b1010000001100101 &
b1010000001100101 1
b1010000001100101 6
b1001 7
b100 >
b1001 <
1;
b100 /
1!
#785000
0!
#790000
b110 =
b110 $
b110 :
b101 /
b101 >
b1001 <
1;
1!
#795000
0!
#800000
b111 =
b111 $
b111 :
b1010000001100101 &
b1010000001100101 1
b1010000001100101 6
b1001 7
b110 >
b1001 <
1;
b110 /
1!
#805000
0!
#810000
b0 '
b0 3
b0 #
b0 5
b1111 %
b1111 4
b0 =
b1111000000000000 &
b1111000000000000 1
b1111000000000000 6
b1011 7
b0 $
b0 :
b111 /
b111 >
b1001 <
1;
1!
#815000
0!
#820000
b1110000 '
b1110000 3
b111 #
b111 5
b1010 %
b1010 4
b1 =
b1 $
b1 :
b11111110 )
b11111110 8
b1010000001110000 &
b1010000001110000 1
b1010000001110000 6
b1010 7
b0 >
b1001 <
1;
b11111110 -
b0 /
1!
#825000
0!
#830000
b10 =
b10 $
b10 :
b1 /
b1 >
b1001 <
1;
1!
#835000
0!
#840000
b11 =
b11 $
b11 :
b1010000001110000 &
b1010000001110000 1
b1010000001110000 6
b1010 7
b10 >
b1001 <
1;
b10 /
1!
#845000
0!
#850000
b100 =
b100 $
b100 :
b11 /
b11 >
b1001 <
1;
1!
#855000
0!
#860000
b101 =
b101 $
b101 :
b1010000001110000 &
b1010000001110000 1
b1010000001110000 6
b1010 7
b100 >
b1001 <
1;
b100 /
1!
#865000
0!
#870000
b110 =
b110 $
b110 :
b101 /
b101 >
b1001 <
1;
1!
#875000
0!
#880000
b111 =
b111 $
b111 :
b1010000001110000 &
b1010000001110000 1
b1010000001110000 6
b1010 7
b110 >
b1001 <
1;
b110 /
1!
#885000
0!
#890000
b0 '
b0 3
b0 #
b0 5
b1111 %
b1111 4
b1 =
b1111000000000000 &
b1111000000000000 1
b1111000000000000 6
b1011 7
b1 $
b1 :
b111 /
b111 >
b1001 <
1;
1!
#895000
0!
#900000
b10 =
b10 $
b10 :
b11111100 )
b11111100 8
b1111000000000000 &
b1111000000000000 1
b1111000000000000 6
b1011 7
b1 >
b1001 <
1;
b11111100 -
b1 /
1!
#905000
0!
#910000
b11111000 )
b11111000 8
b11 =
b11 $
b11 :
b11111000 -
b10 /
b10 >
b1001 <
1;
1!
#915000
0!
#920000
b100 =
b100 $
b100 :
b11110000 )
b11110000 8
b1111000000000000 &
b1111000000000000 1
b1111000000000000 6
b1011 7
b11 >
b1001 <
1;
b11110000 -
b11 /
1!
#925000
0!
#930000
b11100000 )
b11100000 8
b101 =
b101 $
b101 :
b11100000 -
b100 /
b100 >
b1001 <
1;
1!
#935000
0!
#940000
b110 =
b110 $
b110 :
b11000000 )
b11000000 8
b1111000000000000 &
b1111000000000000 1
b1111000000000000 6
b1011 7
b101 >
b1001 <
1;
b11000000 -
b101 /
1!
#945000
0!
#950000
b10000000 )
b10000000 8
b111 =
b111 $
b111 :
b10000000 -
b110 /
b110 >
b1001 <
1;
1!
#955000
0!
#960000
b0 %
b0 4
1,
b0 )
b0 8
b0 &
b0 1
b0 6
b1100 7
b111 >
b1001 <
1;
b0 -
b111 /
1!
#965000
0!
#970000
b111 >
b1001 <
0;
1!
