src/definitions.vh
// definitions.vh
`ifndef DEFINITIONS_VH
`define DEFINITIONS_VH

`define OP_ADD   4'b0000
`define OP_SUB   4'b0001
`define OP_MUL   4'b0010
`define OP_CMP   4'b0011
`define OP_JMP   4'b0100
`define OP_JLT   4'b0101  // Jump if Less Than
`define OP_LDR   4'b0110
`define OP_STR   4'b0111
`define OP_HALT  4'b1111

`define DATA_WIDTH 16
`define ADDR_WIDTH 16
`define REG_COUNT 16

`define NUM_THREADS 8      
`define THREAD_ID_WIDTH 3 

`endif

src/decoder.v
// decoder.v
`include "definitions.vh"

module decoder (
    input [`DATA_WIDTH-1:0] instruction,
    output reg [3:0] opcode,
    output reg [3:0] dest_reg,
    output reg [3:0] src_reg,
    output reg [7:0] immediate
);
    always @(*) begin
        opcode = instruction[15:12];
        dest_reg = instruction[11:8];
        src_reg = instruction[7:4];
        immediate = instruction[7:0]; // For instructions with immediate values
    end
endmodule

src/fetcher.v
// fetcher.v
`include "definitions.vh"

module fetcher (
    input [`ADDR_WIDTH-1:0] pc_in,
    output [`DATA_WIDTH-1:0] instruction,
    input [`DATA_WIDTH-1:0] instr_mem [0:15]
);
    assign instruction = instr_mem[pc_in];
endmodule

src/scheduler.v
// scheduler.v
`include "definitions.vh"

module scheduler #(
    parameter NUM_THREADS = `NUM_THREADS
)(
    input clk,
    input reset,
    input [NUM_THREADS-1:0] active_threads,
    output reg [`THREAD_ID_WIDTH-1:0] scheduled_thread
);
    integer last_thread; 
    integer i;           
    integer thread;      
    reg thread_found;    

    always @(posedge clk or posedge reset) begin
        if (reset) begin
            last_thread <= -1;
            scheduled_thread <= 0;
        end else begin
            thread_found = 0;
            
            // iterate through all threads
            for (i = 1; i <= NUM_THREADS; i = i + 1) begin
                thread = (last_thread + i) % NUM_THREADS;
                
                // check if the current thread is active and no thread has been scheduled yet
                if (active_threads[thread] && !thread_found) begin
                    scheduled_thread <= thread;    
                    last_thread <= thread;         
                    thread_found = 1;              
                end
            end
        end
    end
endmodule

src/compute_core.v
// compute_core.v
`include "definitions.vh"
`include "scheduler.v"  // Bao gồm mô-đun scheduler
`include "fetcher.v"    // Bao gồm mô-đun fetcher
`include "decoder.v"    // Bao gồm mô-đun decoder


module compute_core (
    input clk,
    input reset,
    output reg halt
);
    // Internal registers and memories
    reg [`DATA_WIDTH-1:0] register_file [0:`NUM_THREADS-1][0:`REG_COUNT-1];
    reg [`ADDR_WIDTH-1:0] pc [0:`NUM_THREADS-1];
    reg [`NUM_THREADS-1:0] active_threads;
    reg [`DATA_WIDTH-1:0] data_mem [0:15]; // Shared data memory
    reg [`DATA_WIDTH-1:0] instr_mem [0:15]; // Shared instruction memory

    // Scheduler signals
    wire [`THREAD_ID_WIDTH-1:0] scheduled_thread;

    // Fetcher and Decoder signals
    wire [`DATA_WIDTH-1:0] instruction;
    wire [3:0] opcode;
    wire [3:0] dest_reg;
    wire [3:0] src_reg;
    wire [7:0] immediate;

    // ALU signals
    reg [`DATA_WIDTH-1:0] alu_result;
    reg cmp_flag;

    // Loop variables
    integer i;
    integer current_thread;

    // PC increment control
    reg pc_increment;

    // Temporary register for updated active_threads
    reg [`NUM_THREADS-1:0] next_active_threads;

    // Instantiate Scheduler
    scheduler #(
        .NUM_THREADS(`NUM_THREADS)
    ) scheduler_inst (
        .clk(clk),
        .reset(reset),
        .active_threads(active_threads),
        .scheduled_thread(scheduled_thread)
    );

    // Fetch instruction based on the scheduled thread's PC
    fetcher fetcher_inst (
        .pc_in(pc[scheduled_thread]),
        .instruction(instruction),
        .instr_mem(instr_mem)
    );

    // Decode the instruction
    decoder decoder_inst (
        .instruction(instruction),
        .opcode(opcode),
        .dest_reg(dest_reg),
        .src_reg(src_reg),
        .immediate(immediate)
    );

    // Initialize Instruction Memory
    initial begin
       $readmemh("instruction_memory.mem", instr_mem);
       $display("Instruction Memory Initialized:");
       for (i = 0; i < 16; i = i + 1) begin
           $display("instr_mem[%0d] = %h", i, instr_mem[i]);
       end
    end

    // Initialize Data Memory
    initial begin
       $readmemh("data_memory.mem", data_mem);
       $display("Data Memory Initialized:");
       for (i = 0; i < 16; i = i + 1) begin
           $display("data_mem[%0d] = %h", i, data_mem[i]);
       end
    end

    // Compute Core Logic
    always @(posedge clk or posedge reset) begin
        if (reset) begin
            // Initialize PCs and active threads
            for (i = 0; i < `NUM_THREADS; i = i + 1) begin
                pc[i] <= 0;
                active_threads[i] <= 1; // All threads are active initially
                // Initialize registers
                for (current_thread = 0; current_thread < `REG_COUNT; current_thread = current_thread + 1) begin
                    register_file[i][current_thread] <= 0;
                end
                // Assign thread ID to R15
                register_file[i][15] <= i;
            end
            halt <= 0;
            $display("DUT Reset at time %0t", $time);
        end else if (!halt) begin
            // Initialize next_active_threads with current active_threads
            next_active_threads = active_threads;

            current_thread = scheduled_thread;
            if (active_threads[current_thread]) begin
                pc_increment = 1; // Default to increment

                // Execution
                case (opcode)
                    `OP_ADD: begin
                        alu_result = register_file[current_thread][dest_reg] + register_file[current_thread][src_reg] + immediate;
                        register_file[current_thread][dest_reg] <= alu_result;
                    end
                    `OP_SUB: begin
                        alu_result = register_file[current_thread][dest_reg] - register_file[current_thread][src_reg] - immediate;
                        register_file[current_thread][dest_reg] <= alu_result;
                    end
                    `OP_MUL: begin
                        alu_result = register_file[current_thread][dest_reg] * register_file[current_thread][src_reg];
                        register_file[current_thread][dest_reg] <= alu_result;
                    end
                    `OP_CMP: begin
                        if (register_file[current_thread][dest_reg] < register_file[current_thread][src_reg]) begin
                            cmp_flag <= 1;
                        end else begin
                            cmp_flag <= 0;
                        end
                    end
                    `OP_JMP: begin
                        pc[current_thread] <= {8'b00000000, immediate}; // Assuming immediate is lower 8 bits
                        pc_increment <= 0;
                    end
                    `OP_JLT: begin
                        if (cmp_flag == 1) begin
                            pc[current_thread] <= {8'b00000000, immediate};
                            pc_increment <= 0;
                        end
                    end
                    `OP_LDR: begin
                        register_file[current_thread][dest_reg] <= data_mem[immediate];
                    end
                    `OP_STR: begin
                        data_mem[immediate] <= register_file[current_thread][dest_reg];
                    end
                    `OP_HALT: begin
                        next_active_threads[current_thread] = 0; // Halt the current thread
                        $display("Thread %0d executing HALT. Halting.", current_thread);
                    end
                    default: begin
                        // NOP or undefined instruction
                        $display("Thread %0d encountered undefined opcode %b. No operation performed.", current_thread, opcode);
                    end
                endcase

                // Increment PC if not updated by control instructions
                if (pc_increment) begin
                    pc[current_thread] <= pc[current_thread] + 1;
                end

                // Execution Logging
                $display("Time=%0t | Thread=%0d | PC=%0d | Instruction=%h | Opcode=%b | dest_reg=R%0d | src_reg=R%0d | immediate=%d",
                         $time, current_thread, pc[current_thread], instruction, opcode, dest_reg, src_reg, immediate);
            end

            // Update active_threads
            active_threads <= next_active_threads;

            // Check if all threads have halted
            if (next_active_threads == 0) begin
                halt <= 1;
                $display("All threads have halted at time %0t", $time);
            end
        end
    end

    // Dump waveforms for GTKWave
    initial begin
        $dumpfile("simulation.vcd");
        $dumpvars(0, compute_core); // Replace 'compute_core' with your top-level module name if different
    end

endmodule

testbench/module/compute_core_tb.v
// compute_core_tb.v


module compute_core_tb;

    // Parameters
    parameter DATA_WIDTH = 32;      // Ví dụ cho chiều rộng dữ liệu
    parameter NUM_THREADS = 4;      // Số lượng threads
    parameter REG_COUNT = 16;       // Số lượng thanh ghi trong mỗi thread
    parameter ADDR_WIDTH = 4;       // Chiều rộng địa chỉ bộ nhớ

    // Inputs
    reg clk;
    reg reset;

    // Outputs
    wire halt;

    // Instantiate the compute_core module
    compute_core uut (
        .clk(clk),
        .reset(reset),
        .halt(halt)
    );

    // Clock generation
    always begin
        #5 clk = ~clk;  // Tạo xung đồng hồ với chu kỳ 10 đơn vị thời gian
    end

    // Testbench stimulus
    initial begin
        // Initialize signals
        clk = 0;
        reset = 1;  // Bắt đầu với reset

        // Display header
        $display("Time\tReset\tHalt\tPC[0]\tPC[1]\tPC[2]\tPC[3]");

        // Apply reset and release it after some time
        #10 reset = 0; // Thực hiện reset tại thời điểm t = 0

        // Wait for some clock cycles and observe behavior
        #50; // Đợi một thời gian

        // Test - simulate scheduling and instruction execution
        $display("Running computation...");
        #100; // Đợi một chút để quan sát hoạt động

        // Apply a reset again to see the reset behavior
        reset = 1;
        #10 reset = 0;
        #50;

        // End simulation
        $finish;
    end

    // Monitor the PC and halt signal for debugging
    always @(posedge clk) begin
        $display("%0t\t%0b\t%0b\t%h\t%h\t%h\t%h", $time, reset, halt,
                 uut.pc[0], uut.pc[1], uut.pc[2], uut.pc[3]);
    end

endmodule

src/simulation.vcd
$date
	Sun Dec 01 17:28:43 2024
$end
$version
	Icarus Verilog
$end
$timescale
	1s
$end
$scope module compute_core_tb $end
$scope module uut $end
$var wire 1 ! clk $end
$var wire 1 " reset $end
$var wire 4 # src_reg [3:0] $end
$var wire 3 $ scheduled_thread [2:0] $end
$var wire 4 % opcode [3:0] $end
$var wire 16 & instruction [15:0] $end
$var wire 8 ' immediate [7:0] $end
$var wire 4 ( dest_reg [3:0] $end
$var reg 8 ) active_threads [7:0] $end
$var reg 16 * alu_result [15:0] $end
$var reg 1 + cmp_flag $end
$var reg 1 , halt $end
$var reg 8 - next_active_threads [7:0] $end
$var reg 1 . pc_increment $end
$var integer 32 / current_thread [31:0] $end
$var integer 32 0 i [31:0] $end
$scope module decoder_inst $end
$var wire 16 1 instruction [15:0] $end
$var reg 4 2 dest_reg [3:0] $end
$var reg 8 3 immediate [7:0] $end
$var reg 4 4 opcode [3:0] $end
$var reg 4 5 src_reg [3:0] $end
$upscope $end
$scope module fetcher_inst $end
$var wire 16 6 instruction [15:0] $end
$var wire 16 7 pc_in [15:0] $end
$upscope $end
$scope module scheduler_inst $end
$var wire 8 8 active_threads [7:0] $end
$var wire 1 ! clk $end
$var wire 1 " reset $end
$var parameter 32 9 NUM_THREADS $end
$var reg 3 : scheduled_thread [2:0] $end
$var reg 1 ; thread_found $end
$var integer 32 < i [31:0] $end
$var integer 32 = last_thread [31:0] $end
$var integer 32 > thread [31:0] $end
$upscope $end
$upscope $end
$upscope $end
$enddefinitions $end
$comment Show the parameter values. $end
$dumpall
b1000 9
$end
#0
$dumpvars
bx >
b11111111111111111111111111111111 =
bx <
x;
b0 :
b11111111 8
b0 7
b101000000000110 6
b0 5
b101 4
b110 3
b0 2
b101000000000110 1
b1000 0
b10000 /
x.
bx -
0,
x+
bx *
b11111111 )
b0 (
b110 '
b101000000000110 &
b101 %
b0 $
b0 #
1"
0!
$end
#5
b10000 /
b1000 0
1!
#10
0!
0"
#15
b1111 '
b1111 3
b100 %
b100 4
b0 =
b100000000001111 &
b100000000001111 1
b100000000001111 6
b1 7
b111 >
b1001 <
1;
1.
b0 /
b11111111 -
1!
#20
0!
#25
b110 '
b110 3
b101 %
b101 4
0.
b1 =
b101000000000110 &
b101000000000110 1
b101000000000110 6
b0 7
b1 $
b1 :
b0 >
b1001 <
1;
1!
#30
0!
#35
b10 =
b10 $
b10 :
b101000000000110 &
b101000000000110 1
b101000000000110 6
b0 7
b1 >
b1001 <
1;
1.
b1 /
1!
#40
0!
#45
b11 =
b11 $
b11 :
b10 /
b10 >
b1001 <
1;
1!
#50
0!
#55
b100 =
b100 $
b100 :
b101000000000110 &
b101000000000110 1
b101000000000110 6
b0 7
b11 >
b1001 <
1;
b11 /
1!
#60
0!
#65
b101 =
b101 $
b101 :
b100 /
b100 >
b1001 <
1;
1!
#70
0!
#75
b110 =
b110 $
b110 :
b101000000000110 &
b101000000000110 1
b101000000000110 6
b0 7
b101 >
b1001 <
1;
b101 /
1!
#80
0!
#85
b111 =
b111 $
b111 :
b110 /
b110 >
b1001 <
1;
1!
#90
0!
#95
b0 '
b0 3
b1001 %
b1001 4
b0 =
b0 $
b0 :
b1001000000000000 &
b1001000000000000 1
b1001000000000000 6
b10 7
b111 >
b1001 <
1;
b111 /
1!
#100
0!
#105
b1111 '
b1111 3
b100 %
b100 4
b1 =
b100000000001111 &
b100000000001111 1
b100000000001111 6
b1 7
b1 $
b1 :
b0 /
b0 >
b1001 <
1;
1!
#110
0!
#115
b10 =
b10 $
b10 :
0.
b100000000001111 &
b100000000001111 1
b100000000001111 6
b1 7
b1 >
b1001 <
1;
b1 /
1!
#120
0!
#125
b11 =
b11 $
b11 :
0.
b10 /
b10 >
b1001 <
1;
1!
#130
0!
#135
b100 =
b100 $
b100 :
b100000000001111 &
b100000000001111 1
b100000000001111 6
b1 7
b11 >
b1001 <
1;
0.
b11 /
1!
#140
0!
#145
b101 =
b101 $
b101 :
0.
b100 /
b100 >
b1001 <
1;
1!
#150
0!
#155
b110 =
b110 $
b110 :
b100000000001111 &
b100000000001111 1
b100000000001111 6
b1 7
b101 >
b1001 <
1;
0.
b101 /
1!
#160
b110 '
b110 3
b101 %
b101 4
b101000000000110 &
b101000000000110 1
b101000000000110 6
b0 7
b0 $
b0 :
b11111111111111111111111111111111 =
b10000 /
b1000 0
0!
1"
#165
b10000 /
b1000 0
1!
#170
0!
0"
#175
b1111 '
b1111 3
b100 %
b100 4
b100000000001111 &
b100000000001111 1
b100000000001111 6
b1 7
b0 =
1.
b0 /
b111 >
b1001 <
1;
1!
#180
0!
#185
b110 '
b110 3
b101 %
b101 4
b1 =
b1 $
b1 :
0.
b101000000000110 &
b101000000000110 1
b101000000000110 6
b0 7
b0 >
b1001 <
1;
1!
#190
0!
#195
b10 =
b10 $
b10 :
1.
b1 /
b1 >
b1001 <
1;
1!
#200
0!
#205
b11 =
b11 $
b11 :
b101000000000110 &
b101000000000110 1
b101000000000110 6
b0 7
b10 >
b1001 <
1;
b10 /
1!
#210
0!
#215
b100 =
b100 $
b100 :
b11 /
b11 >
b1001 <
1;
1!
